<!DOCTYPE document PUBLIC "-//UIT//DTD Corpus V1.0//EN" "http://giellatekno.uit.no/dtd/corpus.dtd">
<document xml:lang="isl" id="no_id">
  <header>
    <title/>
    <genre code="facta"/>
    <author>
      <unknown/>
    </author>
    <availability>
      <license type="standard"/>
    </availability>
    <multilingual/>
    <metadata>
      <uncomplete/>
    </metadata>
    <version>XSLtemplate $Revision: 64438 $; file-specific xsl  Revision; common.xsl  $Revision: 68074 $; </version>
  </header>
  <body>
    <p xml:lang="dan">föstudagur, desember 31, 2004</p>
    <p xml:lang="nno">Góður draumur maður</p>
    <p xml:lang="nob">Mig dreymdi að nýtt spil, eða leikur kannski öllu heldur, kom á markaðinn. <errorort correct="Þátttakendur" errorinfo="typo,stem,2-3">Þáttakendur</errorort> voru tveir og plottið eftirfarandi:</p>
    <p>Annar "keppandinn" var tengdur við púlsmæli nokkurs konar, sem greindi hjartslátt, blóðstreymi og önnur líkamleg einkenni. Hinn "keppandinn" studdist við litla bók sem fylgja átti eftir. Í henni voru leiðbeiningar um hvernig mætti koma púlsmælda keppandanum til; ýmsum aðferðum, í formi líkamssnertinga, orða <errorort correct="o.s.frv." errorinfo="abp,0-3">osfrv</errorort>, átti að beita til að æsa þann mælda kynferðislega. Árangurinn kom fram á mælinum og í samræmi við hann gaf bókin nánari leiðbeiningar. Þótti þetta skilvirkur og <errorort correct="sniðugur" errorinfo="vow,stem,e-i">sneðugur</errorort> leikur.</p>
    <p>Ég er ekki frá því að guð hafi í nótt gefið mér góða bissnesshugmynd til að hagnast á fyrir næstu jól.</p>
    <p>Beygingarmynd dagsins: Rignd #</p>
  </body>
</document>
